Metadata-Version: 1.1
Name: hirmr
Version: 0.1
Summary: Probatina para subir a pypi
Home-page: https://github.com/pigmonchu/hirmr
Author: pigmonchu
Author-email: monterdi@gmail.com
License: LGPL v3
Download-URL: https://github.com/pigmonchu/parallel_foreach_submodule/archive/v0.1.tar.gz
Keywords: test example develop
Platform: UNKNOWN
Classifier: Programming Language :: Python
Classifier: Programming Language :: Python :: 2.7
Classifier: Programming Language :: Python :: 3.3
Classifier: Programming Language :: Python :: 3.4
Classifier: Programming Language :: Python :: 3.5
Classifier: Programming Language :: Python :: 3.6
Classifier: Programming Language :: Python :: 3.7
